Sylphiette/Gemini.py
Sylphiette/Terminal.py
Sylphiette/Voices.py
Sylphiette/__init__.py
Sylphiette/base.py
Sylphiette/sylphBot.py
sylphietteiamob-0.1.4.dist-info/METADATA
sylphietteiamob-0.1.4.dist-info/WHEEL
sylphietteiamob-0.1.4.dist-info/top_level.txt
sylphietteiamob-0.1.4.dist-info/RECORD
