Metadata-Version: 2.4
Name: SylphietteIAMob
Version: 0.1.4
Summary: Assistente IA estilo Sylphiette com fala, VTube Studio e Gemini.
Home-page: https://github.com/seuusuario/SylphietteIAMob
Author: __token__
Author-email: seu@email.com
Classifier: Programming Language :: Python :: 3
Classifier: Operating System :: OS Independent
Requires-Python: >=3.7
Requires-Dist: pyttsx3
Requires-Dist: google-generativeai
Requires-Dist: websockets
Requires-Dist: python-osc
Requires-Dist: plyer
Dynamic: author
Dynamic: author-email
Dynamic: classifier
Dynamic: home-page
Dynamic: requires-dist
Dynamic: requires-python
Dynamic: summary
